railroad.py
railroad_diagrams-3.0.1.dist-info/LICENSE
railroad_diagrams-3.0.1.dist-info/METADATA
railroad_diagrams-3.0.1.dist-info/WHEEL
railroad_diagrams-3.0.1.dist-info/top_level.txt
railroad_diagrams-3.0.1.dist-info/RECORD
