Metadata-Version: 2.1
Name: railroad-diagrams
Version: 3.0.1
Summary: Generate SVG railroad syntax diagrams, like on JSON.org.
Home-page: https://github.com/tabatkins/railroad-diagrams
Author: Tab Atkins
Author-email: jackalmage@gmail.com
License: UNKNOWN
Keywords: diagrams,syntax,grammar,railroad diagrams
Platform: UNKNOWN
Classifier: License :: OSI Approved :: MIT License
Classifier: Programming Language :: Python
Classifier: Programming Language :: Python :: 3
Classifier: Programming Language :: Python :: 3.7
Requires-Python: >=3.7
License-File: LICENSE
